kraken_flake8_extensions/__init__.py
kraken_flake8_extensions/base.py
kraken_flake8_extensions/kraken/__init__.py
kraken_flake8_extensions/kraken/kre001.py
kraken_flake8_extensions/kraken/kre002.py
kraken_flake8_extensions/kraken/utils.py
kraken_flake8_extensions/py.typed
kraken_flake8_extensions-0.1.1.dist-info/entry_points.txt
kraken_flake8_extensions-0.1.1.dist-info/LICENSE
kraken_flake8_extensions-0.1.1.dist-info/WHEEL
kraken_flake8_extensions-0.1.1.dist-info/METADATA
kraken_flake8_extensions-0.1.1.dist-info/RECORD
