Metadata-Version: 2.1
Name: kraken-flake8-extensions
Version: 0.1.1
Summary: 
License: MIT
Author: Unknown
Author-email: me@unknown.org
Requires-Python: >=3.6,<4.0
Classifier: License :: OSI Approved :: MIT License
Classifier: Programming Language :: Python :: 3
Classifier: Programming Language :: Python :: 3.6
Classifier: Programming Language :: Python :: 3.7
Classifier: Programming Language :: Python :: 3.8
Classifier: Programming Language :: Python :: 3.9
Classifier: Programming Language :: Python :: 3.10
Classifier: Programming Language :: Python :: 3.11
Requires-Dist: astor (>=0.8.1,<0.9.0)
Project-URL: Bug Tracker, https://github.com/kraken-build/kraken-flake8-extensions/issues
Project-URL: Homepage, https://github.com/kraken-build/kraken-flake8-extensions
Project-URL: Repository, https://github.com/kraken-build/kraken-flake8-extensions
